Workbook
Name N1_APS: '0211'!$BO$14
Name N1_CodeB: '0211'!$N$14
Name N1_CodeS: '0211'!$D$14
Name N1_ComB: '0211'!$X$14
Name N1_ComB_Another: '0211'!$BE$14
Name N1_ComS: '0211'!$W$14
Name N1_ComS_Another: '0211'!$AQ$14
Name N1_ContB: '0211'!$BI$14
Name N1_Control_CommentB: '0211'!$BD$14
Name N1_Control_CommentS: '0211'!$AP$14
Name N1_ContS: '0211'!$BH$14
Name N1_Cr_Val_MrkBZ: '0211'!$AU$14
Name N1_Cr_Val_MrkSZ: '0211'!$AG$14
Name N1_CrBD: '0211'!$AS$14
Name N1_CrBZ: '0211'!$AT$14
Name N1_CrSD: '0211'!$AE$14
Name N1_CrSZ: '0211'!$AF$14
Name N1_DDB: '0211'!$P$14
Name N1_DDS: '0211'!$F$14
Name N1_DGO: '0211'!$BQ$14
Name N1_DifB: '0211'!$U$14
Name N1_DifS: '0211'!$M$14
Name N1_DMrktB: '0211'!$AZ$14
Name N1_DMrktS: '0211'!$AL$14
Name N1_DPB_DDB: '0211'!$AV$14
Name N1_DPS_DDS: '0211'!$AH$14
Name N1_DqualB: '0211'!$BG$14
Name N1_DqualS: '0211'!$BF$14
Name N1_DRB: '0211'!$AR$14
Name N1_DRS: '0211'!$AD$14
Name N1_Dummy1: '0211'!$A$14
Name N1_DZB: '0211'!$O$14
Name N1_DZS: '0211'!$E$14
Name N1_Fin_Res: '0211'!$BL$14
Name N1_H0_11: '0211_Свод'!$D$19
Name N1_H0_13: '0211'!$I$1
Name N1_H0_7: '0211_Свод'!$B$16
Name N1_H0_8: '0211_Свод'!$B$17
Name N1_H0_9: '0211_Свод'!$D$18
Name N1_H0_A: '0211_Свод'!$A$7
Name N1_H0_AnRegistr: '0211'!$B$3
Name N1_H0_AnRegistrTxt: '0211'!$B$4
Name N1_H0_B_INN: '0211_Свод'!$B$8
Name N1_H0_B_KPP: '0211_Свод'!$B$9
Name N1_H0_CodeNU: '0211'!$L$6
Name N1_H0_CodeNU2: '0211'!$AA$6
Name N1_H0_PeriodCode: '0211'!$E$1
Name N1_H0_PeriodTxt: '0211'!$C$5
Name N1_H0_Year: '0211'!$C$1
Name N1_ISIN: '0211'!$BN$14
Name N1_K_ControlB: '0211'!$BC$14
Name N1_K_ControlS: '0211'!$AO$14
Name N1_MainTable: '0211'!$A$14:$BQ$14
Name N1_MaxMrkt: '0211'!$AW$14
Name N1_MinMrkt: '0211'!$AI$14
Name N1_MrktB: '0211'!$AY$14
Name N1_MrktS: '0211'!$AK$14
Name N1_NDSComB: '0211'!$Z$15
Name N1_NDSComS: '0211'!$Y$14
Name N1_PrBvp: '0211'!$R$14

Sheet 0211
B1: Год | C1: <год> | D1: Период (код) | E1: <код> | F1: Корректировка | G1: 0 | H1: Регистр (код) | I1: <H0_13> | J1: КПП | K1: 997950001 | L1: ДУ (код) | M1: Банк | N1: Уровень | O1: 1
B2: АО "Россельхозбанк"
B3: <аналитический регистр>
B4: <registrtxt>
B5: Период: | C5: <ПЕРИОД>
B6: Код НУ | L6: <Code NU> | AA6: <Code NU 2>
B7: ИТОГО | G7: 0 | K7: 0 | L7: 0 | M7: 0 | S7: 0 | T7: 0 | U7: 0 | V7: 0 | W7: 0 | X7: 0 | Y7: 0 | Z7: 0 | AA7: 0 | BK7: 0 | BL7: 0
B8: ФОРМУЛЫ >> | C8: S | D8: F | E8: N
B10: Регистр подготовил | D10: <Операционист>
B11: Код бумаги | C11: Выпуск ценной бумаги | D11: Номер сделки реализации | E11: Дата заключения сделки на реализацию ЦБ | F11: Дата перехода права собств-ти при реализации ЦБ | G11: Количество бумаг, шт. | H11: Код валюты номинала | I11: Код валюты сделки реализации | J11: Цена реализации (на 1 бумагу) | K11: Стоимость реализации | M11: Сумма отклонения фактической выручки ниже рыночной (расчетной) цены, руб. | N11: Номер сделки приобретения | O11: Дата заключения сделки на приобретение ЦБ | P11: Дата перехода права собств-ти при приобретении ЦБ | Q11: Код валюты сделки приобретения | R11: Цена приобретения (за 1 бумагу) | S11: Стоимость приобретения | U11: Сумма превышения стоимости приобретения над рыночной (расчетной) ценой, руб. | V11: Cтоимость приобретенных ценных бумаг, принимаемая для целей налогообложения, руб. | W11: Комиссия уплаченная, руб. | Y11: НДС по комиссии, уплаченной, руб. | AA11: Расходы, принимаемые для целей налогообложения в отчетном налоговом периоде, руб. | AB11: Вид ПФИ | AD11: Дата в учете | AE11: Курс пересчета стоимости реализации в рублевый эквивалент | AF11: Курс ЦБ РФ валюты сделки на дату заключения | AG11: Курс ЦБ РФ валюты котировки на дату заключения | AH11: Разница между датой поставки и датой платежа | AI11: Min цена на дату заключения сделки, сложивш. на ОРЦБ; расчетная цена для ЦБ, не обращ. на ОРЦБ | AN11: Классификатор РЦ сделки | AO11: Классификатор "Доп контроль" сделки | AQ11: Из гр. 22 прочие комиссии, руб. | AR11: Дата в учете | AS11: Курс пересчета стоимости приобретения в рублевый эквивалент | AT11: Курс ЦБ РФ валюты сделки на дату заключения | AU11: Курс ЦБ РФ валюты котировки на дату заключения | AV11: Разница между датой поставки и датой платежа | AW11: Max цена на дату заключения сделки, сложивш. на ОРЦБ; расчетная цена для ЦБ не обращ. на ОРЦБ (расч. цена ПФИ) | BB11: Классификатор РЦ сделки | BC11: Классификатор "Доп контроль" сделки | BE11: Из гр. 23 прочие комиссии, руб. | BF11: Дата переквалификации сделки РЕПО / Займа | BH11: Контрагент по сделке реализации | BI11: Контрагент по сделке приобретения | BJ11: Налоговая группа | BK11: Прибыль (+)/ убыток (-) для целей налогообложения, руб. (гр.11+ гр.12- гр.24) | BL11: Фин. рез для выверки, руб. (гр.11- гр.19) | BM11: Признак льготного налогообложения | BN11: Код ISIN (номер государственной регистрации) ценной бумаги | BO11: Портфель по сделке реализации | BP11: Портфель по сделке приобретения | BQ11: Дата глобальной операции
K12: Сумма в валюте сделки | L12: Сумма, руб. | S12: Сумма в валюте сделки | T12: Сумма, руб. | W12: при реализации | X12: при приобретении | Y12: при реализации | Z12: при приобретении | AB12: по сделке реализации | AC12: по сделке приобретения | AI12: Цена (котировка с учетом К) | AJ12: Ед. изм. | AK12: Источник информации | AL12: Дата котировки | AM12: Котировка (РЦ) | AO12: Код | AP12: Комментарий | AW12: Цена (котировка с учетом К) | AX12: Ед. изм. | AY12: Источник информации | AZ12: Дата котировки | BA12: Котировка (РЦ) | BC12: Код | BD12: Комментарий | BF12: для сделки реализации | BG12: для сделки приобретения
A13: S | B13: 1 | C13: 2 | D13: 3 | E13: 4 | F13: 5 | G13: 6 | H13: 7 | I13: 8 | J13: 9 | K13: 10 | L13: 11 | M13: 12 | N13: 13 | O13: 14 | P13: 15 | Q13: 16 | R13: 17 | S13: 18 | T13: 19 | U13: 20 | V13: 21 | W13: 22 | X13: 23 | Y13: 22.1 | Z13: 23.1 | AA13: 24 | AB13: 25 | AC13: 26 | AD13: S1 | AE13: S2 | AF13: S3 | AG13: S4 | AH13: S5 | AI13: S6 | AJ13: S7 | AK13: S8 | AL13: S9 | AM13: S10 | AN13: S11 | AO13: S12 | AP13: S13 | AQ13: S14 | AR13: B1 | AS13: B2 | AT13: B3 | AU13: B4 | AV13: B5 | AW13: B6 | AX13: B7 | AY13: B8 | AZ13: B9 | BA13: B10 | BB13: B11 | BC13: B12 | BD13: B13 | BE13: B14 | BF13: Т1 | BG13: Т2 | BH13: Т3 | BI13: Т4 | BJ13: Т5 | BK13: Т6 | BL13: V1 | BM13: V2 | BN13: R1 | BO13: M1 | BP13: M2 | BQ13: T7
B14: <SecCode> | C14: <SecName> | D14: <CodeS> | E14: <DZS> | F14: <DDS> | G14: <Qnty> | H14: <VN> | I14: <VPrS> | J14: <PrSvp> | K14: <SumSvp> | L14: <SumSrub> | M14: <DifS> | N14: <CodeB> | O14: <DZB> | P14: <DDB> | Q14: <VPrB> | R14: <PrBvp> | S14: <SumBvp> | T14: <SumBrub> | U14: <DifB> | V14: <SumBtax> | W14: <ComS> | X14: <ComB> | Y14: <NDSComS> | Z14: <NDSComB> | AA14: < RashAll > | AB14: <RFISSS> | AC14: <RFISSB> | AD14: <DRS> | AE14: <CrSD> | AF14: <CrSZ> | AG14: <Cr_Val_MrkSZ> | AH14: <DPS-DDS> | AI14: <MinMrkt> | AJ14: <Val_MarketS> | AK14: <MrktS> | AL14: <DMrktS> | AM14: <QuoteValueS> | AN14: <RCS> | AO14: <K_ControlS> | AP14: <Control_CommentS> | AQ14: <ComS_Another> | AR14: <DRB> | AS14: <CrBD> | AT14: <CrBZ> | AU14: <Cr_Val_MrkBZ> | AV14: <DPB-DDB> | AW14: <MaxMrkt> | AX14: <Val_MarketB> | AY14: <MrktB> | AZ14: <DMrktB> | BA14: <QuoteValueB> | BB14: <RCB> | BC14: <K_ControlB> | BD14: <Control_CommentB> | BE14: <ComB_Another> | BF14: <DqualS> | BG14: <DqualB> | BH14: <ContS> | BI14: <ContB> | BJ14: <SecType> | BK14: <Taxe_All> | BL14: <Fin_Res> | BM14: <SecLax> | BN14: <ISIN> | BO14: <APS> | BP14: <APB> | BQ14: <DGO>
A15: F

Sheet 0211_Свод
A1: Составлено: | C1: <ДатаСоставления>
A2: Исполнитель: | C2: <НомерОпера> | D2: <N11_Операционист>
A7: <H0_A>
A8: ИНН | B8: <H0_B_INN>
A9: КПП | B9: <H0_B_KPP>
A12: Аналитический регистр налогового учета:
A13: Реализация акций, паев и депозитарных расписок
A15: Период:
A16: с | B16: <H0_7>
A17: по | B17: <H0_8>
A18: Группа налогового учета: | D18: <H0_9>
A19: Выпуск ценных бумаг: | D19: <H0_11>
A23: Номер АРНУ | B23: Налоговая группа | C23: Код ценной бумаги | D23: Выпуск ценной бумаги | E23: Финансовый результат от операций с ценными бумагами (без учета корректировки цен в соответствии со ст. 280 НК РФ), руб. | F23: Корректировка (уменьшение) стоимости приобретения в соответствии со ст. 280 НК РФ, руб. | G23: Корректировка (увеличение) стоимости реализации в соответствии со ст. 280 НК РФ, руб. | H23: Комиссии по операциям с ценными бумагами | I23: Прибыль (+)/ убыток (-) для целей налогообложения, руб. | L23: Количество бумаг, шт. | M23: Выручка от реализации для целей налогообложения, руб. | N23: Расходы, принимаемые для целей налогообложения в отчетном (налоговом) периоде, руб. | O23: Стоимость реализации в валюте сделки | P23: Стоимость приобретения в валюте сделки | Q23: Код ISIN (номер государственной регистрации) ценной бумаги
I24: Всего | J24: от реализации
E25: гр. V1 | F25: гр.20 | G25: гр.12 | H25: гр.22+гр.23 | I25: гр.Т6 | J25: гр.Т6 | L25: гр.6 | M25: гр.11 | N25: гр.24 | O25: гр.10 | P25: гр.18
A26: a | B26: b | C26: c | D26: 1 | E26: 2 | F26: 3 | G26: 4 | H26: 5 | I26: 6 | J26: 7 | K26: 8 | L26: 9 | M26: 10 | N26: 11 | O26: 12 | P26: 13 | Q26: d
A27: <RegNum> | B27: <SecType> | C27: <SecCode> | D27: <SecName> | E27: <Fin_Res> | F27: <DifB> | G27: <DifS> | H27: <ComS>+<ComB> | I27: <Taxe_All> | J27: <Taxe_All> | K27: <Taxe_All> | L27: <Qnty> | M27: <SumSrub> | N27: <RashAll> | O27: <SumSvp> | P27: <SumBvp> | Q27: <ISIN>

Sheet 0212
A1: Составлено: | C1: <ДатаСоставления>
A2: Исполнитель: | C2: <НомерОпера> | D2: <Операционист>
A7: <H0_A>
A8: ИНН | B8: <H0_B_INN>
A9: КПП | B9: <H0_B_KPP>
A10: Форма № | B10: <H0_3>
A12: Аналитический регистр налогового учета:
A13: Реализация (погашение) купонных облигаций, номинал которых выражен в валюте РФ
A15: Период:
A16: с | B16: <H0_7>
A17: по | B17: <H0_8>
A18: Группа налогового учета: | C18: <H0_9>
A19: Выпуск ценных бумаг: | C19: <H0_11>
A20: <H0_13>
A24: Код бумаги | B24: Выпуск ценной бумаги | C24: Номер сделки реализации (погашения) | D24: Дата заключения сделки на реализацию (дата погашения) ЦБ | E24: Дата перехода права собств-ти при реализации (дата погашения) ЦБ | F24: Количество бумаг, шт. | G24: Цена реализации, % от номинала | H24: Стоимость реализации (погашения), руб. | I24: НКД полученный при реализации (погашении), руб. | J24: Выручка от реализации (погашения) для целей налогообложения, руб. | L24: Сумма отклонения фактической выручки ниже рыночной (расчетной) цены, руб. | M24: Процентный доход, начисленный за отчетный (налоговый) период, руб. | P24: Доходы, выплаченные эмитентом при частичном погашении номинала, учитываемые в отчетном (налоговом) периоде, руб. | Q24: Номер сделки приобретения | R24: Дата заключения сделки на приобретение ЦБ | S24: Дата перехода права собств-ти при приобретении ЦБ | T24: Цена приобретения, в % от номинала | U24: Стоимость приобретения, руб. | V24: НКД уплаченный при приобретении, руб. | W24: Учтено в текущем отчетном (налоговом) периоде, руб. | Y24: Учтено в предыдущих налоговых периодах при частичном погашении номинала, руб. | AA24: Комиссия уплаченная, руб. | AC24: НДС по комиссии, уплаченной, руб. | AE24: Расходы, принимаемые для целей налогообложения в отчетном налоговом периоде, руб. | AF24: Номинал на дату реализации ценной бумаги | AG24: Номинал на дату приобретения ценной бумаги | AH24: Вид ПФИ | AJ24: Погашение - 1, реализация -0 | AK24: Дата в учете | AL24: Курс пересчета стоимости реализации в рублевый эквивалент | AM24: Стоимость реализации (погашения) в валюте сделки, руб. | AN24: Min цена на дату заключения сделки, сложивш. на ОРЦБ; расчетная цена для ЦБ, не обращ. на ОРЦБ | AS24: Классификатор РЦ сделки | AT24: Классификатор "Доп контроль" сделки | AV24: Из гр. 23 прочие комиссии, руб. | AW24: Дата в учете | AX24: Курс пересчета стоимости реализации в рублевый эквивалент | AY24: Стоимость приобретения в валюте сделки, руб. | AZ24: Max цена на дату заключения сделки, сложивш. на ОРЦБ; расчетная цена для ЦБ не обращ. на ОРЦБ (расч. цена ПФИ) | BE24: Классификатор РЦ сделки | BF24: Классификатор "Доп контроль" сделки | BH24: Из гр. 24 прочие комиссии, руб. | BI24: Сумма превышения стоимости приобретения над рыночной (расчетной) ценой, руб. | BJ24: НКД, уплаченный при приобретении, уменьшающий, руб. | BM24: Отметка о наличии выплат купона от эмитента до начала налогового периода (1 - да, 0 - нет) | BN24: Процентный доход, учтенный для целей налогообложения в предыдущем налоговом периоде, но не полученный от эмитента на начало отчетного (налогового) периода | BP24: Купонный доход, полученный от эмитента при погашении купонов в отчетном (налоговом) периоде (кроме купона, полученного при погашении бумаги), руб. | BQ24: Дата выплаты по последнему купону в отчетном периоде | BR24: Контроль процентного дохода | BS24: Доходы, выплаченные эмитентом при частичном погашении номинала, в валюте номинала | BW24: Коэф-т погашения номинала (за период до начала текущего отчетного (налогового) периода) | BX24: Стоимость приобретения, признанная расходами в отчетном (налоговом) периоде (до оценки "на рыночность"), в валюте сделки | BY24: Дата переквалификации сделки РЕПО / Займа | CA24: Контрагент по сделке реализации | CB24: Контрагент по сделке приобретения | CC24: Налоговая группа | CD24: Прибыль (+)/ убыток (-) для целей налогообложения, руб. | CG24: Фин. рез для выверки, руб. (гр.10- гр.11+ гр.13- гр.25+ гр.21+ гр.23+ гр.24) | CH24: Признак льготного налогообложения | CI24: Накопленный купонный доход за отчетный период, руб. | CJ24: Код ISIN (номер государственной регистрации) ценной бумаги | CK24: Индексируемый номинал | CP24: Портфель по сделке реализации | CQ24: Портфель по сделке приобретения | CR24: Дата глобальной операции
J25: Всего | K25: в том числе: суммы % дохода, учтенные при налогообложении до начала текущего отчетного (налогового) периода | M25: Всего | N25: Льготная ставка | O25: Общая ставка | W25: Сумма превышения стоимости приобретения над рыночной (расчетной) ценой | X25: Cтоимость приобретенных ценных бумаг, принимаемая для целей налогообложения | Y25: Сумма превышения стоимости приобретения над рыночной (расчетной) ценой | Z25: Cтоимость приобретенных ценных бумаг, принимаемая для целей налогообложения | AA25: при реализации | AB25: при приобретении (с учетом ч/п при V17=да) | AC25: при реализации | AD25: при приобретении | AH25: по сделке реализации | AI25: по сделке приобретения | AN25: Цена (котировка с учетом К) | AO25: Ед. изм. | AP25: Источник информации | AQ25: Дата котировки | AR25: Котировка (РЦ) | AT25: Код | AU25: Комментарий | AZ25: Цена (котировка с учетом К) | BA25: Ед. изм. | BB25: Источник информации | BC25: Дата котировки | BD25: Котировка (РЦ) | BF25: Код | BG25: Комментарий | BJ25: процентные доходы прошлых налоговых периодов | BK25: процентные доходы текущего налогового периода | BL25: доходы от реализации (погашения) | BN25: Период, дней | BO25: Сумма, руб. | BS25: Всего | BT25: до 01.01.2015г. | BU25: с 01.01.2015 - всего | BV25: За отчетный (налоговый) период | BY25: для сделки реализации | BZ25: для сделки приобретения | CD25: Всего (гр.Т7+ гр.Т8) | CE25: от реализации (погашения) (гр.10+ гр.12- гр.25) | CF25: сальдо процентных доходов и расходов (гр.13 - гр.11) | CK25: На дату приобретения /дату начала отчетного периода | CL25: На дату реализации | CM25: Положительная разница (Т10-Т9) | CN25: Отрицательная разница (Т10-Т9) | CO25: До отчетного периода
A26: 1 | B26: 2 | C26: 3 | D26: 4 | E26: 5 | F26: 6 | G26: 7 | H26: 8 | I26: 9 | J26: 10 | K26: 11 | L26: 12 | M26: 13 | N26: 13.1 | O26: 13.2 | P26: 14 | Q26: 15 | R26: 16 | S26: 17 | T26: 18 | U26: 19 | V26: 20 | W26: 21 | X26: 22 | Y26: 22.1 | Z26: 22.2 | AA26: 23 | AB26: 24 | AC26: 23.1 | AD26: 24.1 | AE26: 25 | AF26: 26 | AG26: 27 | AH26: 28 | AI26: 29 | AJ26: S0 | AK26: S1 | AL26: S2 | AM26: S3 | AN26: S4 | AO26: S5 | AP26: S6 | AQ26: S7 | AR26: S8 | AS26: S9 | AT26: S10 | AU26: S11 | AV26: S12 | AW26: B1 | AX26: B2 | AY26: B3 | AZ26: B4 | BA26: B5 | BB26: B6 | BC26: B7 | BD26: B8 | BE26: B9 | BF26: B10 | BG26: B11 | BH26: B12 | BI26: B13 | BJ26: К1 | BK26: К2 | BL26: К3 | BM26: К4 | BN26: К5 | BO26: К6 | BP26: К7 | BQ26: К8 | BR26: К9 | BS26: А1 | BT26: А2 | BU26: А3 | BV26: А4 | BW26: А5 | BX26: А6 | BY26: Т1 | BZ26: Т2 | CA26: Т3 | CB26: Т4 | CC26: Т5 | CD26: Т6 | CE26: Т7 | CF26: Т8 | CG26: V1 | CH26: V2 | CI26: V3 | CJ26: R1 | CK26: Т9 | CL26: Т10 | CM26: Т11 | CN26: Т12 | CO26: Т13 | CP26: M1 | CQ26: M2 | CR26: T14
A27: <SecCode> | B27: <SecName> | C27: <CodeS> | D27: <DZS> | E27: <DDS> | F27: <Qnty> | G27: <PrSNom> | H27: <SumSrub> | I27: <NkdSvp> | J27: <SumAllrub> | K27: <NKDminusRub> | L27: <DifS> | M27: <NkdRepRub> | N27: <NkdRepRub1> | O27: <NkdRepRub2> | P27: <AmortVNrep> | Q27: <CodeB> | R27: <DZB> | S27: <DDB> | T27: <PrBnom> | U27: <SumBrub> | V27: <NkdBvp> | W27: <DifSumBRub> | X27: <SumBNRub> | Y27: <DifSumBRub_AmortPrev> | Z27: <SumBRub_AmortPrev> | AA27: <ComS> | AB27: <ComB> | AC27: <NDSComS> | AD27: <NDSComB> | AE27: <RashAll> | AF27: <Nom_ DDS> | AG27: <Nom_ DDB> | AH27: <RFISSS> | AI27: <RFISSB> | AJ27: <SellType> | AK27: <DRS> | AL27: <CrSD> | AM27: <SumSvp> | AN27: <MinMrkt> | AO27: <Val_MarketS> | AP27: <MrktS> | AQ27: <DMrktS> | AR27: <QuoteValueS> | AS27: <RCS> | AT27: <K_ControlS> | AU27: <Control_CommentS> | AV27: <ComS_Another> | AW27: <DRB> | AX27: <CrBD> | AY27: <SumBvp> | AZ27: <MaxMrkt> | BA27: <Val_MarketB> | BB27: <MrktB> | BC27: <DMrktB> | BD27: <QuoteValueB> | BE27: <RCB> | BF27: <K_ControlB> | BG27: <Control_CommentB> | BH27: <ComB_Another> | BI27: <DifB> | BJ27: <NkdBprevRub> | BK27: <NkdBrepRub> | BL27: <NkdBsellRub> | BM27: <ifCoupPrev> | BN27: <Tprev> | BO27: <NkdPrevVN> | BP27: <CoupVN> | BQ27: <LastCoupDate> | BR27: <ControlNKD> | BS27: <AmortVN> | BT27: <AmortVN_before> | BU27: <AmortVN_after> | BV27: <AmortVNPer> | BW27: <KSumBvn> | BX27: <SumBvp_exps> | BY27: <DqualS> | BZ27: <DqualB> | CA27: <ContS> | CB27: <ContB> | CC27: <SecType> | CD27: <Taxe_All> | CE27: <Taxe_Amort> | CF27: <Taxe_NKD> | CG27: <Fin_Res> | CH27: <SecLax> | CI27: <NkdRepRubAll> | CJ27: <ISIN> | CK27: <Nom_H01> | CL27: <Nom_H02> | CM27: <PlusNom_IN> | CN27: <MinusNom_IN> | CO27: <Nom_IN_Before> | CP27: <APS> | CQ27: <APB> | CR27: <DGO>
A29: Примечание:
A30: Регистр формируется в головном офисе в целом по Банку
A32: <ДолжностьРуководителяПодразделения> | E32: <РуководительПодразделения>
D33: (подпись) | E33: Ф.И.О.
A35: <ДолжностьОперациониста> | D35: =N2_Операционист -> <Операционист>
C36: (подпись) | D36: Ф.И.О.

Sheet 0212_Свод
A1: Составлено: | C1: =N2_ДатаСоставления -> <ДатаСоставления>
A2: Исполнитель: | C2: ='0212'!C2 -> <НомерОпера> | D2: =N2_Операционист -> <Операционист>
A7: ='0212'!A7 -> <H0_A>
A8: ИНН | B8: =N2_H0_B_INN -> <H0_B_INN>
A9: КПП | B9: =N2_H0_B_KPP -> <H0_B_KPP>
A12: Аналитический регистр налогового учета:
A13: ='0212'!$A$13 -> Реализация (погашение) купонных облигаций, номинал которых выражен в валюте РФ
A15: Период:
A16: с | B16: ='0212'!B16 -> <H0_7>
A17: по | B17: ='0212'!B17 -> <H0_8>
A18: Группа налогового учета: | D18: ='0212'!C18 -> <H0_9>
A19: Выпуск ценных бумаг: | D19: ='0212'!C19 -> <H0_11>
A23: Номер АРНУ | B23: Налоговая группа | C23: Код ценной бумаги | D23: Выпуск ценной бумаги | E23: Финансовый результат от операций с ценными бумагами (без учета корректировки цен в соответствии со ст. 280 НК РФ), руб. | F23: Корректировка (уменьшение) стоимости приобретения в соответствии со ст. 280 НК РФ, руб. | G23: Корректировка (увеличение) стоимости реализации в соответствии со ст. 280 НК РФ, руб. | H23: Комиссии по операциям с ценными бумагами | I23: Прибыль (+)/ убыток (-) для целей налогообложения, руб. | L23: Количество бумаг, шт. | M23: Выручка от реализации (погашения) для целей налогообложения, руб. | N23: Расходы, принимаемые для целей налогообложения в отчетном (налоговом) периоде, руб. | O23: Стоимость реализации (погашения) в валюте сделки | P23: Стоимость приобретения, признанная расходами в отчетном (налоговом) периоде (до оценки "на рыночность"), в валюте сделки | Q23: Процентный доход, начисленный за отчетный (налоговый) период, руб. | S23: Суммы % дохода, учтенные при налогообложении до начала текущего отчетного (налогового) периода, руб. | T23: НКД полученный при реализации (погашении), в валюте сделки | U23: НКД уплаченный при приобретении, в валюте сделки | V23: Доходы, выплаченные эмитентом при частичном погашении номинала, учитываемые в отчетном (налоговом периоде), в валюте номинала | W23: Купонный доход, полученный от эмитента при погашении купонов в отчетном периоде, в валюте номинала (без учета процентного дохода с кодом "2") | X23: Суммы % дохода, учтенные при налогообложении до начала отчетного периода, в валюте номинала | Y23: Накопленный купонный доход за отчетный период, руб. | Z23: Код ISIN (номер государственной регистрации) ценной бумаги
I24: Всего | J24: от реализации (в т.ч. частич. погашения номинала) | K24: внереализационные (процентные) доходы/ расходы | Q24: Льготная ставка | R24: Общая ставка
E25: гр. V1 | F25: гр.21 | G25: гр.12 | H25: гр.23+гр.24 | I25: гр.Т6 | J25: гр.Т7 | K25: гр.Т8 | L25: гр.6 | M25: гр.10 | N25: гр.25 | O25: гр.S3 | P25: гр.А6 | Q25: гр.13.1 | R25: гр.13.2 | S25: гр.11 | T25: гр.9 | U25: гр.20 | V25: гр.14 | W25: сумма по гр.К7 без учета дополнительного процентного дохода с кодом "2" + часть гр. 9 с учетом гр.S0 | X25: гр.К6 | Y25: V3
A26: a | B26: b | C26: c | D26: 1 | E26: 2 | F26: 3 | G26: 4 | H26: 5 | I26: 6 | J26: 7 | K26: 8 | L26: 9 | M26: 10 | N26: 11 | O26: 12 | P26: 13 | Q26: 14 | R26: 15 | S26: 16 | T26: 17 | U26: 18 | V26: 19 | W26: 20 | X26: 21 | Y26: 22 | Z26: d
A27: <RegNum> | B27: <SecType> | C27: <SecCode> | D27: <SecName> | E27: <Fin_Res> | F27: <DifSumBRub> | G27: <DifS> | H27: <ComS>+<ComB> | I27: <Taxe_All> | J27: <Taxe_Amort> | K27: <Taxe_NKD> | L27: <Qnty> | M27: <SumAllRub> | N27: <RashAll> | O27: <SumSvp> | P27: <SumBvp_exps> | Q27: <NkdRepRub1> | R27: <NkdRepRub2> | S27: <NKDminusRub> | T27: <NkdSvp> | U27: <NkdBvp> | V27: <AmortVNrep> | W27: <CoupVN> + <NkdSvp> | X27: <NkdPrevVN> | Y27: <NkdRepRubAll> | Z27: <ISIN>

Sheet 0213
B1: Год | C1: <H0_Year> | D1: Период (код) | E1: <H0_PeriodCode> | F1: Корректировка | G1: 0 | H1: Регистр (код) | I1: <H0_13> | J1: КПП | K1: 997950001 | L1: ДУ (код) | M1: Банк | N1: Уровень | O1: 1
B2: АО "Россельхозбанк"
B3: <H0_AnRegistr>
B4: <H0_AnRegistrTxt>
B5: Период: | C5: <H0_PeriodTxt>
B6: Код НУ | N6: <H0_CodeNU_N> | Q6: <H0_CodeNU_Q> | AJ6: <H0_CodeNU_AJ>
B7: ИТОГО | K7: 0 | M7: 0 | N7: 0 | O7: 0 | P7: 0 | Q7: 0 | U7: 0 | V7: 0 | W7: 0 | AB7: 0 | AF7: 0 | AG7: 0 | AH7: 0 | AI7: 0 | AJ7: 0 | AP7: 0 | AQ7: 0 | AR7: 0
B8: ФОРМУЛЫ >> | C8: S | D8: F | E8: N
B10: Регистр подготовил | D10: <Операционист>
B11: Код бумаги | C11: Выпуск ценной бумаги | D11: Номер сделки реализации (погашения) | E11: Дата заключения сделки реализации (дата погашения) ЦБ | F11: Дата перехода права собств-ти при реализации (дата погашения) ЦБ | G11: Номинал, руб. | H11: Дата размещения | I11: Дата погашения | J11: Средневзвешенная цена размещения, % от номинала | K11: Количество бумаг, шт. | L11: Цена реализации, % от номинала | M11: Стоимость реализации (погашения), руб. | N11: Процентный доход за период с даты приобретения до даты начала отчетного периода, руб. | O11: Процентный доход за период с даты приобретения по дату реализации, руб. | P11: Процентный доход, начисленный за отчетный (налоговый) период, руб. | Q11: Выручка от реализации (погашения) для целей налогообложения, руб. | R11: Min цена на дату заключения сделки, сложивш. на ОРЦБ; расчетная цена для ЦБ, не обращ. на ОРЦБ | U11: Сумма отклонения фактической выручки ниже рыночной (расчетной) цены, руб. | V11: Комиссия, уплаченная при реализации, руб. | W11: НДС по комиссии, уплаченной при реализации, руб | X11: Номер сделки приобретения | Y11: Дата заключения сделки приобретения ЦБ | Z11: Дата перехода права собств-ти при приобретении ЦБ | AA11: Цена приобретения, в % от номинала | AB11: Стоимость приобретения, руб. | AC11: Max цена на дату заключения сделки, сложивш. на ОРЦБ; расчетная цена для ЦБ не обращ. на ОРЦБ (расч. цена ПФИ) | AF11: Сумма превышения стоимости приобретения над рыночной (расчетной) ценой, руб. | AG11: Cтоимость приобретенных ценных бумаг, принимаемая для целей налогообложения, руб. | AH11: Комиссия, уплаченная при приобретении, руб. | AI11: НДС по комиссии, уплаченной при приобретении, руб. | AJ11: Расходы, принимаемые для целей налогообложения в отчетном налоговом периоде, руб. | AK11: Дата переквалификации сделки РЕПО / Займа | AM11: Контрагент по сделке реализации | AN11: Контрагент по сделке приобретения | AO11: Налоговая группа | AP11: Прибыль (+)/ убыток (-) для целей налогообложения, руб. | AS11: Признак льготного налогообложения | AT11: Код ISIN (номер государственной регистрации) ценной бумаги | AU11: Дата глобальной операции
R12: Цена, в % от номинала | S12: Источник информации | T12: Дата котировки | AC12: Цена, в % от номинала | AD12: Источник информации | AE12: Дата котировки | AK12: для сделки реализации | AL12: для сделки приобретения | AP12: Всего (гр.Т7+ гр.Т8) | AQ12: от реализации (погашения) (гр.16+ гр.20- гр.33) | AR12: сальдо процентных доходов и расходов (гр.15)
A13: S | B13: 1 | C13: 2 | D13: 3 | E13: 4 | F13: 5 | G13: 6 | H13: 7 | I13: 8 | J13: 9 | K13: 10 | L13: 11 | M13: 12 | N13: 13 | O13: 14 | P13: 15 | Q13: 16 | R13: 17 | S13: 18 | T13: 19 | U13: 20 | V13: 21 | W13: 21.1 | X13: 22 | Y13: 23 | Z13: 24 | AA13: 25 | AB13: 26 | AC13: 27 | AD13: 28 | AE13: 29 | AF13: 30 | AG13: 31 | AH13: 32 | AI13: 32.1 | AJ13: 33 | AK13: T1 | AL13: ="Т"&RIGHT(AK13,LEN(AK13)-1)+1 -> Т2 | AM13: ="Т"&RIGHT(AL13,LEN(AL13)-1)+1 -> Т3 | AN13: ="Т"&RIGHT(AM13,LEN(AM13)-1)+1 -> Т4 | AO13: ="Т"&RIGHT(AN13,LEN(AN13)-1)+1 -> Т5 | AP13: ="Т"&RIGHT(AO13,LEN(AO13)-1)+1 -> Т6 | AQ13: ="Т"&RIGHT(AP13,LEN(AP13)-1)+1 -> Т7 | AR13: ="Т"&RIGHT(AQ13,LEN(AQ13)-1)+1 -> Т8 | AS13: V1 | AT13: R1 | AU13: T9
B14: <SecCode> | C14: <SecName> | D14: <CodeS> | E14: <DZS> | F14: <DDS> | G14: <Nom> | H14: <DAuс> | I14: <Dexp> | J14: <PrAucNom> | K14: <Qnty> | L14: <PrSNom> | M14: <SumSrub> | N14: <NkdBefVN> | O14: <NKDownVN> | P14: <NkdRepRub> | Q14: <SumAllrub> | R14: <MinMrkt> | S14: <MrktS> | T14: <DMrktS> | U14: <DifS> | V14: <ComS> | W14: <NDSComS> | X14: <CodeB> | Y14: <DZB> | Z14: <DDB> | AA14: <PrBnom> | AB14: <SumBrub> | AC14: <MaxMrkt> | AD14: <MrktB> | AE14: <DMrktB> | AF14: <DifB> | AG14: <SumBtax> | AH14: <ComB> | AI14: <NDSComB> | AJ14: <RashAll> | AK14: <DqualS> | AL14: <DqualB> | AM14: <ContS> | AN14: <ContB> | AO14: <SecType> | AP14: <Taxe_All> | AQ14: <Taxe_Amort> | AR14: <Taxe_NKD> | AS14: <SecLax> | AT14: <ISIN> | AU14: <DGO>
A15: F

Sheet 0215
B1: Год | C1: <год> | D1: Период (код) | E1: <код> | F1: Корректировка | G1: 0 | H1: Регистр (код) | I1: <H0_13> | J1: КПП | K1: 997950001 | L1: ДУ (код) | M1: Банк | N1: Уровень | O1: 1
B2: АО "Россельхозбанк"
B3: <аналитический регистр>
B4: <registrtxt>
B5: Период: | C5: <ПЕРИОД>
B6: Код НУ | N6: <CodeNU_N> | O6: <CodeNU_O> | AL6: <CodeNU_AL> | BR6: <CodeNU_BR> | BW6: <CodeNU_BW> | BY6: <CodeNU_BY>
B7: ИТОГО | G7: 0 | K7: 0 | L7: 0 | M7: 0 | N7: 0 | O7: 0 | P7: 0 | Q7: 0 | R7: 0 | S7: 0 | T7: 0 | Z7: 0 | AA7: 0 | AB7: 0 | AC7: 0 | AD7: 0 | AE7: 0 | AF7: 0 | AG7: 0 | AH7: 0 | AI7: 0 | AJ7: 0 | AK7: 0 | AL7: 0 | AT7: 0 | BF7: 0 | BP7: 0 | BQ7: 0 | BR7: 0 | BS7: 0 | BT7: 0 | BU7: 0 | BV7: 0 | BW7: 0 | BX7: 0 | BY7: 0 | CA7: 0 | CB7: 0 | CC7: 0 | CD7: 0 | CF7: 0 | CG7: 0 | CM7: 0 | CN7: 0 | CO7: 0 | CP7: 0 | CR7: 0
B8: ФОРМУЛЫ >> | C8: S | D8: F | E8: N
B10: Регистр подготовил | D10: <Операционист>
B11: Код бумаги | C11: Выпуск ценной бумаги | D11: Номер сделки реализации (погашения) | E11: Дата заключения сделки на реализацию (дата погашения) ЦБ | F11: Дата перехода права собств-ти при реализации (дата погашения) ЦБ | G11: Количество бумаг, шт. | H11: Код валюты номинала | I11: Код валюты сделки реализации | J11: Цена реализации, % от номинала | K11: Стоимость реализации (погашения) | M11: НКД полученный при реализации (погашении) | O11: Выручка от реализации (погашения) для целей налогообложения, руб. | Q11: Сумма отклонения фактической выручки ниже рыночной (расчетной) цены, руб. | R11: Процентный доход, начисленный за отчетный (налоговый) период, руб. | S11: Доходы, выплаченные эмитентом при частичном погашении номинала, учитываемые в отчетном (налоговом периоде) | U11: Номер сделки приобретения | V11: Дата заключения сделки на приобретение ЦБ | W11: Дата перехода права собств-ти при приобретении ЦБ | X11: Код валюты сделки приобретения | Y11: Цена приобретения, в % от номинала | Z11: Стоимость приобретения | AB11: НКД уплаченный при приобретении | AD11: Учтено в текущем отчетном (налоговом) периоде, руб. | AF11: Учтено в предыдущих налоговых периодах при частичном погашении номинала, руб. | AH11: Комиссия уплаченная, руб. | AJ11: НДС по комиссии, уплаченной, руб. | AL11: Расходы, принимаемые для целей налогообложения в отчетном (налоговом) периоде, руб. | AM11: Номинал на дату реализации ценной бумаги | AN11: Номинал на дату приобретения ценной бумаги | AO11: Вид ПФИ | AQ11: Погашение - 1, реализация -0 | AR11: Дата в учете | AS11: Курс пересчета стоимости реализации в рублевый эквивалент | AT11: Разница между датами платежа и поставки | AU11: Min цена на дату заключения сделки, сложивш. на ОРЦБ; расчетная цена для ЦБ, не обращ. на ОРЦБ | AZ11: Классификатор РЦ сделки | BA11: Классификатор "Доп контроль" сделки | BC11: Из гр. 31 прочие комиссии, руб. | BD11: Дата в учете | BE11: Курс пересчета стоимости приобретения в рублевый эквивалент | BF11: Разница между датами платежа и поставки | BG11: Max цена на дату заключения сделки, сложивш. на ОРЦБ; расчетная цена для ЦБ не обращ. на ОРЦБ (расч. цена ПФИ) | BL11: Классификатор РЦ сделки | BM11: Классификатор "Доп контроль" сделки | BO11: Из гр. 32 прочие комиссии, руб. | BP11: Сумма превышения стоимости приобретения над рыночной (расчетной) ценой, руб. | BQ11: НКД, уплаченный при приобретении, уменьшающий, руб. | BT11: Отметка о наличии выплат купона от эмитента до начала налогового периода (1 - да, 0 - нет) | BU11: Процентный доход, учтенный для целей налогообложения в предыдущем налоговом периоде, но не полученный от эмитента на начало отчетного (налогового) периода | BX11: Купонный доход, полученный от эмитента при погашении купонов в отчетном (налоговом) периоде (кроме купона, полученного при погашении бумаги) | BZ11: Дата выплаты по последнему купону в отчетном периоде | CA11: Доходы, выплаченные эмитентом при частичном погашении номинала, в валюте номинала | CE11: Коэф-т погашения номинала (за период до начала текущего отчетного (налогового) периода) | CF11: Стоимость приобретения, признанная расходами в отчетном (налоговом) периоде (до оценки "на рыночность"), в валюте сделки | CG11: Стоимость приобретения, признанная расходами до НОП при частичном погашении номинала (до оценки "на рыночность"), в валюте сделки | CH11: Дата переквалификации сделки РЕПО / Займа | CJ11: Контрагент по сделке реализации | CK11: Контрагент по сделке приобретения | CL11: Налоговая группа | CM11: Прибыль (+)/ убыток (-) для целей налогообложения, руб. | CP11: Фин. рез для выверки, руб. (гр.14- гр.15+ гр.17- гр.33+ гр.29+ гр.31+ гр.32) | CQ11: Признак льготного налогообложения | CR11: Накопленный купонный доход за отчетный период, руб. | CS11: Код ISIN (номер государственной регистрации) ценной бумаги | CT11: Портфель по сделке реализации | CU11: Портфель по сделке приобретения | CV11: Дата глобальной операции
K12: Сумма в валюте сделки | L12: Сумма, руб. | M12: Сумма в валюте сделки | N12: Сумма, руб. | O12: Всего | P12: в том числе: суммы % дохода, учтенные при налогообложении до начала текущего отчетного (налогового) периода | S12: Сумма в валюте номинала | T12: Сумма, руб. | Z12: Сумма в валюте сделки | AA12: Сумма, руб. | AB12: Сумма в валюте сделки | AC12: Сумма, руб. | AD12: Сумма превышения стоимости приобретения над рыночной (расчетной) ценой | AE12: Cтоимость приобретенных ценных бумаг, принимаемая для целей налогообложения | AF12: Сумма превышения стоимости приобретения над рыночной (расчетной) ценой | AG12: Cтоимость приобретенных ценных бумаг, принимаемая для целей налогообложения | AH12: при реализации | AI12: при приобретении (с учетом ч/п при V17=да) | AJ12: при реализации | AK12: при приобретении | AO12: по сделке реализации | AP12: по сделке приобретения | AU12: Цена (котировка с учетом К) | AV12: Ед. изм. | AW12: Источник информации | AX12: Дата котировки | AY12: Котировка (РЦ) | BA12: Код | BB12: Комментарий | BG12: Цена (котировка с учетом К) | BH12: Ед. изм. | BI12: Источник информации | BJ12: Дата котировки | BK12: Котировка (РЦ) | BM12: Код | BN12: Комментарий | BQ12: процентные доходы прошлых налоговых периодов | BR12: процентные доходы текущего налогового периода | BS12: доходы от реализации (погашения) | BU12: Период, дней | BV12: Сумма в валюте номинала | BW12: Сумма, руб. | BX12: Сумма в валюте номинала | BY12: Сумма, руб. | CA12: Всего | CB12: до 01.01.2015г. | CC12: с 01.01.2015 - всего | CD12: За отчетный (налоговый) период | CH12: для сделки реализации | CI12: для сделки приобретения | CM12: Всего (гр.Т7+ гр.Т8) | CN12: от реализации (погашения) (гр.14+ гр.16- гр.33) | CO12: сальдо процентных доходов и расходов (гр.17 - гр.15)
A13: S | B13: 1 | C13: 2 | D13: 3 | E13: 4 | F13: 5 | G13: 6 | H13: 7 | I13: 8 | J13: 9 | K13: 10 | L13: 11 | M13: 12 | N13: 13 | O13: 14 | P13: 15 | Q13: 16 | R13: 17 | S13: 18 | T13: 19 | U13: 20 | V13: 21 | W13: 22 | X13: 23 | Y13: 24 | Z13: 25 | AA13: 26 | AB13: 27 | AC13: 28 | AD13: 29 | AE13: 30 | AF13: 30.1 | AG13: 30.2 | AH13: 31 | AI13: 32 | AJ13: 31.1 | AK13: 32.1 | AL13: 33 | AM13: 34 | AN13: 35 | AO13: 36 | AP13: 37 | AQ13: S0 | AR13: S1 | AS13: S2 | AT13: S3 | AU13: S4 | AV13: S5 | AW13: S6 | AX13: S7 | AY13: S8 | AZ13: S9 | BA13: S10 | BB13: S11 | BC13: S12 | BD13: B1 | BE13: B2 | BF13: B3 | BG13: B4 | BH13: B5 | BI13: B6 | BJ13: B7 | BK13: B8 | BL13: B9 | BM13: B10 | BN13: B11 | BO13: B12 | BP13: B13 | BQ13: К1 | BR13: К2 | BS13: К3 | BT13: К4 | BU13: К5 | BV13: К6 | BW13: К7 | BX13: К8 | BY13: К9 | BZ13: К10 | CA13: А1 | CB13: А2 | CC13: А3 | CD13: А4 | CE13: А5 | CF13: А6 | CG13: А7 | CH13: Т1 | CI13: Т2 | CJ13: Т3 | CK13: Т4 | CL13: Т5 | CM13: Т6 | CN13: Т7 | CO13: Т8 | CP13: V1 | CQ13: V2 | CR13: V3 | CS13: R1 | CT13: M1 | CU13: M2 | CV13: T9
B14: <SecCode> | C14: <SecName> | D14: <CodeS> | E14: <DZS> | F14: <DDS> | G14: <Qnty> | H14: <VN> | I14: <VPrS> | J14: <PrSNom> | K14: <SumSvp> | L14: <SumSrub> | M14: <NkdSvp> | N14: <NkdSrub> | O14: <SumAllrub> | P14: <NKDminusRub> | Q14: <DifS> | R14: <NKDRepRub> | S14: <AmortVNrep> | T14: <AmortRubrep> | U14: <CodeB> | V14: <DZB> | W14: <DDB> | X14: <VPrB> | Y14: <PrBnom> | Z14: <SumBvp> | AA14: <SumBrub> | AB14: <NkdBvp> | AC14: <NkdBrub> | AD14: <DifSumBRub> | AE14: <SumBNRub> | AF14: <DifSumBRub_AmortPrev> | AG14: <SumBRub_AmortPrev> | AH14: <ComS> | AI14: <ComB> | AJ14: <NDSComS> | AK14: <NDSComB> | AL14: <RashAll> | AM14: <Nom_DDS> | AN14: <Nom_DDB> | AO14: <RFISSS> | AP14: <RFISSB> | AQ14: <SellType> | AR14: <DRS> | AS14: <CrSD> | AT14: <DPS-DDS> | AU14: <MinMrkt> | AV14: <Val_MarketS> | AW14: <MrktS> | AX14: <DMrktS> | AY14: <QuoteValueS> | AZ14: <RCS> | BA14: <K_ControlS> | BB14: <Control_CommentS> | BC14: <ComS_Another> | BD14: <DRB> | BE14: <CrBD> | BF14: <DPB-DDB> | BG14: <MaxMrkt> | BH14: <Val_MarketB> | BI14: <MrktB> | BJ14: <DMrktB> | BK14: <QuoteValueB> | BL14: <RCB> | BM14: <K_ControlB> | BN14: <Control_CommentB> | BO14: <ComB_Another> | BP14: <DifB> | BQ14: <NkdBprevRub> | BR14: <NkdBrepRub> | BS14: <NkdBsellRub> | BT14: <ifCoupPrev> | BU14: <Tprev> | BV14: <NkdPrevVN> | BW14: <NkdPrevRub> | BX14: <CoupVN> | BY14: <CoupRub> | BZ14: <LastCoupDate> | CA14: <AmortVN> | CB14: <AmortVN_before> | CC14: <AmortVN_after> | CD14: <AmortVNPer> | CE14: <КSumBvn> | CF14: <SumBvp_exps> | CG14: <SumBvpPrev_exps> | CH14: <DqualS> | CI14: <DqualB> | CJ14: <ContS> | CK14: <ContB> | CL14: <SecType> | CM14: <Taxe_All> | CN14: <Taxe_Amort> | CO14: <Taxe_NKD> | CP14: <Fin_Res> | CQ14: <SecLax> | CR14: <NkdRepRubAll> | CS14: <ISIN> | CT14: <APS> | CU14: <APB> | CV14: <DGO>
A15: F

Sheet 0215_Свод
A1: Составлено: | C1: <ДатаСоставления>
A2: Исполнитель: | C2: <НомерОпера> | D2: <Операционист>
A7: <H0_A>
A8: ИНН | B8: <H0_B_INN>
A9: КПП | B9: <H0_B_KPP>
A12: Аналитический регистр налогового учета:
A13: Реализация (погашение) купонных облигаций, номинал которых выражен в иностранной валюте
A15: Период:
A16: с | B16: <H0_7>
A17: по | B17: <H0_8>
A18: Группа налогового учета: | D18: <H0_9>
A19: Выпуск ценных бумаг: | D19: <H0_11>
A23: Номер АРНУ | B23: Налоговая группа | C23: Код ценной бумаги | D23: Выпуск ценной бумаги | E23: Финансовый результат от операций с ценными бумагами (без учета корректировки цен в соответствии со ст. 280 НК РФ), руб. | F23: Корректировка (уменьшение) стоимости приобретения в соответствии со ст. 280 НК РФ, руб. | G23: Корректировка (увеличение) стоимости реализации в соответствии со ст. 280 НК РФ, руб. | H23: Комиссии по операциям с ценными бумагами | I23: Прибыль (+)/ убыток (-) для целей налогообложения, руб. | L23: Количество бумаг, шт. | M23: Выручка от реализации (погашения) для целей налогообложения, руб. | N23: Расходы, принимаемые для целей налогообложения в отчетном (налоговом) периоде, руб. | O23: Стоимость реализации (погашения) в валюте сделки | P23: Стоимость приобретения, признанная расходами в отчетном (налоговом) периоде (до оценки "на рыночность"), в валюте сделки | Q23: Процентный доход, начисленный за отчетный (налоговый) период, руб. | R23: Суммы % дохода, учтенные при налогообложении до начала текущего отчетного (налогового) периода, руб. | S23: НКД полученный при реализации (погашении), в валюте сделки | T23: НКД уплаченный при приобретении, в валюте сделки | U23: Доходы, выплаченные эмитентом при частичном погашении номинала, учитываемые в отчетном (налоговом периоде), в валюте номинала | V23: Купонный доход, полученный от эмитента при погашении купонов в отчетном периоде, в валюте номинала | W23: Суммы % дохода, учтенные при налогообложении до начала отчетного периода, руб. | X23: Накопленный купонный доход за отчетный период, руб. | Y23: Код ISIN (номер государственной регистрации) ценной бумаги
I24: Всего | J24: от реализации (в т.ч. частич. погашения номинала) | K24: внереализационные (процентные) доходы/ расходы
E25: гр. V1 | F25: гр.29 | G25: гр.16 | H25: гр.31+гр.32 | I25: гр.Т6 | J25: гр.Т7 | K25: гр.Т8 | L25: гр.6 | M25: гр.14 | N25: гр.33 | O25: гр.10 | P25: гр.А6 | Q25: гр.17 | R25: гр.15 | S25: гр.12 | T25: гр.27 | U25: гр.18 | V25: гр.К8 + часть гр. 12 с учетом гр.S0 | W25: гр.К6 | X25: V3
A26: a | B26: b | C26: c | D26: 1 | E26: 2 | F26: 3 | G26: 4 | H26: 5 | I26: 6 | J26: 7 | K26: 8 | L26: 9 | M26: 10 | N26: 11 | O26: 12 | P26: 13 | Q26: 14 | R26: 15 | S26: 16 | T26: 17 | U26: 18 | V26: 19 | W26: 20 | X26: 21 | Y26: d
A27: <RegNum> | B27: <SecType> | C27: <SecCode> | D27: <SecName> | E27: <Fin_Res> | F27: <DifSumBRub> | G27: <DifS> | H27: <ComS>+<ComB> | I27: <Taxe_All> | J27: <Taxe_Amort> | K27: <Taxe_NKD> | L27: <Qnty> | M27: <SumAllRub> | N27: <RashAll> | O27: <SumSvp> | P27: <SumBvp_exps> | Q27: <NkdRepRub> | R27: <NKDminusRub> | S27: <NkdSvp> | T27: <NkdBvp> | U27: <AmortVNrep> | V27: <CoupVN> + <NkdSvp> | W27: <NkdPrevRub> | X27: <NkdRepRubAll> | Y27: <ISIN>

Sheet 0216
B1: Год | C1: <H0_Year> | D1: Период (код) | E1: <PeriodCode> | F1: Корректировка | G1: 0 | H1: Регистр (код) | I1: <H0_13> | J1: КПП | K1: 997950001 | L1: ДУ (код) | M1: Банк | N1: Уровень | O1: 1
B2: АО "Россельхозбанк"
B3: <H0_AnRegistr>
B4: <H0_AnRegistrTxt>
B5: Период: | C5: <H0_PeriodTxt>
B6: Код НУ | Q6: <H0_CodeNU_Q> | U6: <H0_CodeNU_U> | AP6: <H0_CodeNU_AP>
B7: ИТОГО | L7: 0 | O7: 0 | P7: 0 | Q7: 0 | R7: 0 | S7: 0 | T7: 0 | U7: 0 | Y7: 0 | Z7: 0 | AA7: 0 | AH7: 0 | AL7: 0 | AM7: 0 | AN7: 0 | AO7: 0 | AP7: 0 | AX7: 0 | AY7: 0 | AZ7: 0
B8: ФОРМУЛЫ >> | C8: S | D8: F | E8: N
B10: Регистр подготовил | D10: <Операционист>
B11: Код ценной бумаги | C11: Выпуск ценной бумаги | D11: Номер сделки реализации (погашения) | E11: Дата заключения сделки реализации (дата погашения) ЦБ | F11: Дата перехода права собств-ти при реализации (дата погашения) ЦБ | G11: Номинал | H11: Валюта номинала | I11: Код валюты сделки реализации | J11: Дата размещения | K11: Дата погашения | L11: Количество бумаг, шт. | M11: Цена реализации, % от номинала | N11: Стоимость реализации (погашения) | P11: Процентный доход за период с даты приобретения до даты начала отчетного периода | R11: Процентный доход за период с даты приобретения до даты реализации (погашения) | T11: Процентный доход, начисленный за отчетный (налоговый) период, руб. | U11: Выручка от реализации (погашения) для целей налогообложения, руб | V11: Min цена на дату заключения сделки, сложивш. на ОРЦБ; расчетная цена для ЦБ, не обращ. на ОРЦБ | Y11: Сумма отклонения фактической выручки ниже рыночной (расчетной) цены, руб. | Z11: Комиссия, уплаченная при реализации, руб. | AA11: НДС по комиссии, уплаченной при реализации, руб | AB11: Номер сделки приобретения | AC11: Дата заключения сделки приобретения ЦБ | AD11: Дата перехода права собств-ти при приобретении ЦБ | AE11: Цена приобретения, в % от номинала | AF11: Код валюты сделки приобретения | AG11: Стоимость приобретения | AI11: Max цена на дату заключения сделки, сложивш. на ОРЦБ; расчетная цена для ЦБ не обращ. на ОРЦБ (расч. цена ПФИ) | AL11: Сумма превышения стоимости приобретения над рыночной (расчетной) ценой, руб. | AM11: Cтоимость приобретенных ценных бумаг, принимаемая для целей налогообложения, руб. | AN11: Комиссия, уплаченная при приобретении, руб. | AO11: НДС по комиссии, уплаченной при приобретении, руб. | AP11: Расходы, принимаемые для целей налогообложения в отчетном налоговом периоде, руб. | AQ11: Курс пересчета стоимости реализации в рублевый эквивалент | AR11: Курс пересчета стоимости приобретения в рублевый эквивалент | AS11: Дата переквалификации сделки РЕПО / Займа | AU11: Контрагент по сделке реализации | AV11: Контрагент по сделке приобретения | AW11: Налоговая группа | AX11: Прибыль (+)/ убыток (-) для целей налогообложения, руб. | BA11: Признак льготного налогообложения | BB11: Код ISIN (номер государственной регистрации) ценной бумаги | BC11: Дата глобальной операции
N12: Сумма в валюте сделки | O12: Сумма, руб. | P12: в валюте номинала | Q12: в рублях | R12: в валюте номинала | S12: в рублях | V12: Цена, в % от номинала | W12: Источник информации | X12: Дата котировки | AG12: Сумма в валюте сделки | AH12: Сумма, руб. | AI12: Цена, в % от номинала | AJ12: Источник информации | AK12: Дата котировки | AS12: для сделки реализации | AT12: для сделки приобретения | AX12: Всего (гр.Т9+ гр.Т10) | AY12: от реализации (погашения) (гр.20+ гр.24- гр.39) | AZ12: сальдо процентных доходов и расходов (гр.19)
A13: S | B13: 1 | C13: 2 | D13: 3 | E13: 4 | F13: 5 | G13: 6 | H13: 7 | I13: 8 | J13: 9 | K13: 10 | L13: 11 | M13: 12 | N13: 13 | O13: 14 | P13: 15 | Q13: 16 | R13: 17 | S13: 18 | T13: 19 | U13: 20 | V13: 21 | W13: 22 | X13: 23 | Y13: 24 | Z13: 25 | AA13: 25.1 | AB13: 26 | AC13: 27 | AD13: 28 | AE13: 29 | AF13: 30 | AG13: 31 | AH13: 32 | AI13: 33 | AJ13: 34 | AK13: 35 | AL13: 36 | AM13: 37 | AN13: 38 | AO13: 38.1 | AP13: 39 | AQ13: Т1 | AR13: ="Т"&RIGHT(AQ13,LEN(AQ13)-1)+1 -> Т2 | AS13: ="Т"&RIGHT(AR13,LEN(AR13)-1)+1 -> Т3 | AT13: ="Т"&RIGHT(AS13,LEN(AS13)-1)+1 -> Т4 | AU13: ="Т"&RIGHT(AT13,LEN(AT13)-1)+1 -> Т5 | AV13: ="Т"&RIGHT(AU13,LEN(AU13)-1)+1 -> Т6 | AW13: ="Т"&RIGHT(AV13,LEN(AV13)-1)+1 -> Т7 | AX13: ="Т"&RIGHT(AW13,LEN(AW13)-1)+1 -> Т8 | AY13: ="Т"&RIGHT(AX13,LEN(AX13)-1)+1 -> Т9 | AZ13: ="Т"&RIGHT(AY13,LEN(AY13)-1)+1 -> Т10 | BA13: V1 | BB13: R1 | BC13: T11
B14: <SecCode> | C14: <SecName> | D14: <CodeS> | E14: <DZS> | F14: <DDS> | G14: <Nom> | H14: <VN> | I14: <VPrS> | J14: <DAuс> | K14: <Dexp> | L14: <Qnty> | M14: <PrSnom> | N14: <SumSvp> | O14: <SumSrub> | P14: <NkdBefVN> | Q14: <NkdBefRub> | R14: <NKDownVN> | S14: <NKDownRub> | T14: <NkdRepRub> | U14: <SumAllrub> | V14: <MinMrkt> | W14: <MrktS> | X14: <DMrktS> | Y14: <DifS> | Z14: <ComS> | AA14: <NDSComS> | AB14: <CodeB> | AC14: <DZB> | AD14: <DDB> | AE14: <PrBnom> | AF14: <VPrB> | AG14: <SumBvp> | AH14: <SumBrub> | AI14: <MaxMrkt> | AJ14: <MrktB> | AK14: <DMrktB> | AL14: <DifB> | AM14: <SumBtax> | AN14: <ComB> | AO14: <NDSComB> | AP14: <RashAll> | AQ14: <CrSD> | AR14: <CrBD> | AS14: <DqualS> | AT14: <DqualB> | AU14: <ContS> | AV14: <ContB> | AW14: <SecType> | AX14: <Taxe_All> | AY14: <Taxe_Amort> | AZ14: <Taxe_NKD> | BA14: <SecLax> | BB14: <ISIN> | BC14: <DGO>
A15: F
